README.md
setup.py
saudacoes/__init__.py
saudacoes/mensagens.py
saudacoes.egg-info/PKG-INFO
saudacoes.egg-info/SOURCES.txt
saudacoes.egg-info/dependency_links.txt
saudacoes.egg-info/top_level.txt