Metadata-Version: 2.4
Name: saudacoes
Version: 0.1
Summary: Um pacote de exemplo com mensagens de saudação.
Author: Teu Nome
Classifier: Programming Language :: Python :: 3
Classifier: License :: OSI Approved :: MIT License
Classifier: Operating System :: OS Independent
Requires-Python: >=3.6
Dynamic: author
Dynamic: classifier
Dynamic: description
Dynamic: description-content-type
Dynamic: requires-python
Dynamic: summary
